hypermodern_python_koa/__init__.py
hypermodern_python_koa/console.py
hypermodern_python_koa/wikipedia.py
hypermodern_python_koa-0.1.0.dist-info/LICENSE
hypermodern_python_koa-0.1.0.dist-info/METADATA
hypermodern_python_koa-0.1.0.dist-info/WHEEL
hypermodern_python_koa-0.1.0.dist-info/entry_points.txt
hypermodern_python_koa-0.1.0.dist-info/RECORD
