Metadata-Version: 2.3
Name: hypermodern-python-koa
Version: 0.1.0
Summary: 
Author: kadamopoulos
Author-email: constantinosadamopoulos@gmail.com
Requires-Python: >=3.12,<4.0
Classifier: Programming Language :: Python :: 3
Classifier: Programming Language :: Python :: 3.12
Classifier: Programming Language :: Python :: 3.13
Requires-Dist: click (>=8.1.7,<9.0.0)
Requires-Dist: desert (>=2022.9.22,<2023.0.0)
Requires-Dist: marshmallow (>=3.25.1,<4.0.0)
Requires-Dist: requests (>=2.32.3,<3.0.0)
